{"name":"CortanaDisabler","tagline":"Disable Windows 10 Cortana completely by permanently stopping the process SearchUI.","body":"# CortanaDisable\r\n\r\nEven when you disable Cortana from the start menu, the process SearchUI still runs in the background. It's been known to consume a lot of resources. I read about a solution at a forum, and though it is quite simple, I figured I would make a simple console utility to handle it for you quicker.\r\n\r\n\r\n### Created and tested on Microsoft Windows 10 Enterprise 10.0.10240 Build 10240.\r\n","google":"UA-66396656-1","note":"Don't delete this file! It's used internally to help with page regeneration."}